plover_wpm_meter/__init__.py
plover_wpm_meter/resources_rc.py
plover_wpm_meter/strokes_meter_ui.py
plover_wpm_meter/wpm_meter_ui.py
plover_wpm_meter/textstat/__init__.py
plover_wpm_meter/textstat/textstat.py
plover_wpm_meter-0.2.3.dist-info/DESCRIPTION.rst
plover_wpm_meter-0.2.3.dist-info/METADATA
plover_wpm_meter-0.2.3.dist-info/RECORD
plover_wpm_meter-0.2.3.dist-info/WHEEL
plover_wpm_meter-0.2.3.dist-info/entry_points.txt
plover_wpm_meter-0.2.3.dist-info/metadata.json
plover_wpm_meter-0.2.3.dist-info/top_level.txt
plover_wpm_meter-0.2.3.dist-info/zip-safe
