Metadata-Version: 2.0
Name: plover-wpm-meter
Version: 0.2.3
Summary: A meter to show your typing speed in Plover
Home-page: https://github.com/arxanas/plover_wpm_meter
Author: Waleed Khan
Author-email: me@waleedkhan.name
License: GNU General Public License v3 (GPLv3)
Keywords: plover plover_plugin
Platform: UNKNOWN
Classifier: Development Status :: 4 - Beta
Classifier: Environment :: Plugins
Classifier: Intended Audience :: End Users/Desktop
Classifier: License :: OSI Approved :: GNU General Public License v3 (GPLv3)
Classifier: Operating System :: OS Independent
Classifier: Programming Language :: Python :: 3
Classifier: Programming Language :: Python :: 3.4
Classifier: Programming Language :: Python :: 3.5
Classifier: Programming Language :: Python :: 3.6
Requires-Dist: plover (>=4.0.0.dev2)
Requires-Dist: textstat (==0.3.1)
